{
   "mesh": {
      "file": "motor0.smb",
      "out-file": "motor_mesh"
   },
   "model-file": "motor.egads",
   "space-dis": {
      "basis-type": "nedelec",
      "degree": 1
   },
   "steady": true,
   "time-dis": {
   },
   "lin-solver": {
      "print-lvl": 2,
      "max-iter": 500
   },
   "newton": {
      "print-lvl": 1,
      "rel-tol": 1e-8,
      "abs-tol": 1e-8
   },
   "components": {
      "stator": {
         "material": "steel",
         "attr": 10,
         "linear": true
      },
      "rotor": {
         "material": "steel",
         "attr": 11,
         "linear": true
      },
      "magnets": {
         "material": "NdFeB",
         "attr": 5,
         "linear": true,
         "poles": 16
      }
   },
   "material-lib-path": "../src/material_library.json"
}
